changelog/.gitempty
dkist_processing_math/__init__.py
dkist_processing_math/arithmetic.py
dkist_processing_math/feature.py
dkist_processing_math/linear_algebra.py
dkist_processing_math/statistics.py
dkist_processing_math/tests/__init__.py
dkist_processing_math/tests/conftest.py
dkist_processing_math/tests/test_arithmetic.py
dkist_processing_math/tests/test_feature.py
dkist_processing_math/tests/test_linear_algebra.py
dkist_processing_math/tests/test_statistics.py
dkist_processing_math/tests/test_transform.py
dkist_processing_math/transform/__init__.py
dkist_processing_math/transform/affine.py
dkist_processing_math/transform/binary.py
dkist_processing_math/transform/binning.py
dkist_processing_math/transform/hough.py
docs/Makefile
docs/changelog.rst
docs/conf.py
docs/index.rst
docs/landing_page.rst
docs/make.bat
docs/requirements.txt
licenses/LICENSE.rst
dkist_processing_math-2.2.1.dist-info/METADATA
dkist_processing_math-2.2.1.dist-info/WHEEL
dkist_processing_math-2.2.1.dist-info/top_level.txt
dkist_processing_math-2.2.1.dist-info/RECORD
