Metadata-Version: 2.4
Name: dkist-processing-math
Version: 2.2.1
Summary: Common math functionality used in the DKIST calibrations suite
Author-email: NSO / AURA <dkistdc@nso.edu>
License: BSD-3-Clause
Project-URL: Homepage, https://nso.edu/dkist/data-center/
Project-URL: Repository, https://bitbucket.org/dkistdc/dkist-processing-math/
Project-URL: Documentation, https://docs.dkist.nso.edu/projects/math
Project-URL: Help, https://nso.atlassian.net/servicedesk/customer/portal/5
Classifier: Programming Language :: Python
Classifier: Programming Language :: Python :: 3
Classifier: Programming Language :: Python :: 3.11
Requires-Python: >=3.11
Requires-Dist: dkist-processing-common>=4.0.0
Requires-Dist: numpy>=1.24.0
Requires-Dist: scikit-image>=0.21.0
Requires-Dist: scipy>=1.11.0
Requires-Dist: peakutils>=1.3.3
Provides-Extra: test
Requires-Dist: pytest; extra == "test"
Requires-Dist: pytest-cov; extra == "test"
Requires-Dist: pytest-mock; extra == "test"
Requires-Dist: hypothesis; extra == "test"
Requires-Dist: towncrier; extra == "test"
Provides-Extra: docs
Requires-Dist: sphinx; extra == "docs"
Requires-Dist: sphinx-astropy; extra == "docs"
Requires-Dist: sphinx-changelog; extra == "docs"
Requires-Dist: sphinx-autoapi; extra == "docs"
Requires-Dist: pytest; extra == "docs"
Requires-Dist: towncrier; extra == "docs"
Requires-Dist: dkist-sphinx-theme; extra == "docs"
